cavaconn/__init__.py
cavaconn-0.2.dist-info/DESCRIPTION.rst
cavaconn-0.2.dist-info/METADATA
cavaconn-0.2.dist-info/RECORD
cavaconn-0.2.dist-info/WHEEL
cavaconn-0.2.dist-info/metadata.json
cavaconn-0.2.dist-info/top_level.txt
