Metadata-Version: 2.0
Name: cavaconn
Version: 0.2
Summary: Create database engines for SQL servers, and easily connect to APIs
Home-page: https://github.com/cavagrill/cavaconn
Author: Jordan Bramble
Author-email: tech@cava.com
License: MIT
Download-URL: https://github.com/cavagrill/cavaconn/tarball/0.2
Platform: UNKNOWN
Requires-Dist: psycopg2-binary
Requires-Dist: PyYAML
Requires-Dist: sqlalchemy
Requires-Dist: pymssql
